selfhash/__init__.py
selfhash/selfhash.py
selfhash-0.1.2.1.dist-info/LICENSE
selfhash-0.1.2.1.dist-info/METADATA
selfhash-0.1.2.1.dist-info/WHEEL
selfhash-0.1.2.1.dist-info/top_level.txt
selfhash-0.1.2.1.dist-info/RECORD
