Metadata-Version: 2.1
Name: selfhash
Version: 0.1.2.1
Summary: A package to self hash and verify a python script
Home-page: https://github.com/ronaldstoner/selfhash-python
Author: Ron Stoner
Author-email: ron@stoner.com
License: UNKNOWN
Keywords: self hash verify python script integrity checksum
Platform: UNKNOWN
Classifier: Development Status :: 4 - Beta
Classifier: Intended Audience :: Developers
Classifier: Topic :: Software Development :: Build Tools
Classifier: Programming Language :: Python :: 3.6
Classifier: Programming Language :: Python :: 3.7
Classifier: Programming Language :: Python :: 3.8
Classifier: License :: OSI Approved :: MIT License
License-File: LICENSE
